dsassign/__init__.py
dsassign/dsassign.py
dsassign/dsassign_pdf.py
dsassign/test.tplx
dsassign/to_ok.py
dsassign/to_pdf.py
tests/__init__.py
tests/test_export.py
tests/test_strip.py
dsassign-0.0.8.dist-info/LICENSE
dsassign-0.0.8.dist-info/METADATA
dsassign-0.0.8.dist-info/WHEEL
dsassign-0.0.8.dist-info/entry_points.txt
dsassign-0.0.8.dist-info/top_level.txt
dsassign-0.0.8.dist-info/RECORD
