Metadata-Version: 2.1
Name: dsassign
Version: 0.0.8
Summary: Jupyter notebook assignment formatting and distribution
Home-page: https://github.com/DS-100/ds-assign
Author: John DeNero, Will Huang
Author-email: denero@berkeley.edu, wwhuang@berkeley.edu
License: UNKNOWN
Platform: UNKNOWN
Classifier: Programming Language :: Python :: 3
Classifier: License :: OSI Approved :: MIT License
Classifier: Operating System :: OS Independent
Requires-Dist: pyyaml
Requires-Dist: nbformat
Requires-Dist: ipython
Requires-Dist: nbconvert (>=5.6.0)
Requires-Dist: tqdm
Requires-Dist: setuptools
